dicom_fuzzer/__init__.py
dicom_fuzzer/__main__.py
dicom_fuzzer/analytics/__init__.py
dicom_fuzzer/analytics/campaign_analytics.py
dicom_fuzzer/analytics/visualization.py
dicom_fuzzer/cli/__init__.py
dicom_fuzzer/cli/calibrate.py
dicom_fuzzer/cli/corpus.py
dicom_fuzzer/cli/coverage_fuzz.py
dicom_fuzzer/cli/create_html_report.py
dicom_fuzzer/cli/differential.py
dicom_fuzzer/cli/generate_report.py
dicom_fuzzer/cli/llm.py
dicom_fuzzer/cli/main.py
dicom_fuzzer/cli/output.py
dicom_fuzzer/cli/persistent.py
dicom_fuzzer/cli/realtime_monitor.py
dicom_fuzzer/cli/samples.py
dicom_fuzzer/cli/state.py
dicom_fuzzer/cli/stress.py
dicom_fuzzer/cli/study.py
dicom_fuzzer/cli/target.py
dicom_fuzzer/cli/tls.py
dicom_fuzzer/core/__init__.py
dicom_fuzzer/core/atheris_integration.py
dicom_fuzzer/core/byte_mutator.py
dicom_fuzzer/core/config.py
dicom_fuzzer/core/config_validator.py
dicom_fuzzer/core/corpus.py
dicom_fuzzer/core/corpus_distillation.py
dicom_fuzzer/core/corpus_manager.py
dicom_fuzzer/core/corpus_minimizer.py
dicom_fuzzer/core/coverage_correlation.py
dicom_fuzzer/core/coverage_fuzzer.py
dicom_fuzzer/core/coverage_guided_fuzzer.py
dicom_fuzzer/core/coverage_guided_mutator.py
dicom_fuzzer/core/coverage_instrumentation.py
dicom_fuzzer/core/coverage_tracker.py
dicom_fuzzer/core/crash_analyzer.py
dicom_fuzzer/core/crash_deduplication.py
dicom_fuzzer/core/crash_triage.py
dicom_fuzzer/core/dicom_grammar.py
dicom_fuzzer/core/dicom_series.py
dicom_fuzzer/core/dicom_tls_fuzzer.py
dicom_fuzzer/core/differential_fuzzer.py
dicom_fuzzer/core/dimse_fuzzer.py
dicom_fuzzer/core/enhanced_reporter.py
dicom_fuzzer/core/error_recovery.py
dicom_fuzzer/core/exceptions.py
dicom_fuzzer/core/fuzzing_session.py
dicom_fuzzer/core/generator.py
dicom_fuzzer/core/grammar_fuzzer.py
dicom_fuzzer/core/gui_monitor.py
dicom_fuzzer/core/input_to_state.py
dicom_fuzzer/core/lazy_loader.py
dicom_fuzzer/core/llm_fuzzer.py
dicom_fuzzer/core/mutation_minimization.py
dicom_fuzzer/core/mutation_scheduler.py
dicom_fuzzer-1.7.2.dist-info/METADATA
dicom_fuzzer-1.7.2.dist-info/WHEEL
dicom_fuzzer-1.7.2.dist-info/entry_points.txt
dicom_fuzzer-1.7.2.dist-info/licenses/LICENSE
dicom_fuzzer-1.7.2.dist-info/RECORD
