Metadata-Version: 2.4
Name: dicom-fuzzer
Version: 1.7.2
Summary: A professional-grade DICOM fuzzing tool for healthcare security testing
Project-URL: Homepage, https://github.com/Dashtid/dicom-fuzzer
Project-URL: Documentation, https://github.com/Dashtid/dicom-fuzzer/tree/main/docs
Project-URL: Repository, https://github.com/Dashtid/dicom-fuzzer.git
Project-URL: Bug Tracker, https://github.com/Dashtid/dicom-fuzzer/issues
Project-URL: Changelog, https://github.com/Dashtid/dicom-fuzzer/blob/main/CHANGELOG.md
Author-email: David Dashti <david@dashti.se>
License: MIT
License-File: LICENSE
Keywords: cybersecurity,dicom,fuzzing,healthcare,medical-imaging,pacs,security,vulnerability-testing
Classifier: Development Status :: 4 - Beta
Classifier: Intended Audience :: Healthcare Industry
Classifier: Intended Audience :: Information Technology
Classifier: License :: OSI Approved :: MIT License
Classifier: Operating System :: OS Independent
Classifier: Programming Language :: Python :: 3
Classifier: Programming Language :: Python :: 3.11
Classifier: Programming Language :: Python :: 3.12
Classifier: Programming Language :: Python :: 3.13
Classifier: Programming Language :: Python :: 3.14
Classifier: Topic :: Scientific/Engineering :: Medical Science Apps.
Classifier: Topic :: Security
Classifier: Topic :: Software Development :: Testing
Requires-Python: >=3.11
Requires-Dist: cryptography>=41.0.0
Requires-Dist: numpy>=1.24.0
Requires-Dist: psutil>=5.9.0
Requires-Dist: pydantic-settings>=2.0.0
Requires-Dist: pydantic>=2.0.0
Requires-Dist: pydicom>=2.4.0
Requires-Dist: pynetdicom>=2.0.0
Requires-Dist: python-dotenv>=1.0.0
Requires-Dist: rich>=13.0.0
Requires-Dist: structlog>=23.0.0
Requires-Dist: tqdm>=4.66.0
Provides-Extra: all
Requires-Dist: matplotlib>=3.5.0; extra == 'all'
Requires-Dist: plotly>=5.0.0; extra == 'all'
Requires-Dist: prometheus-client>=0.21.0; extra == 'all'
Requires-Dist: pynetdicom[apps]>=2.0.0; extra == 'all'
Requires-Dist: redis>=5.2.0; extra == 'all'
Requires-Dist: seaborn>=0.12.0; extra == 'all'
Provides-Extra: differential
Requires-Dist: python-gdcm>=3.0.0; (platform_system != 'Windows') and extra == 'differential'
Provides-Extra: distributed
Requires-Dist: redis>=5.2.0; extra == 'distributed'
Provides-Extra: metrics
Requires-Dist: prometheus-client>=0.21.0; extra == 'metrics'
Provides-Extra: network
Requires-Dist: pynetdicom[apps]>=2.0.0; extra == 'network'
Provides-Extra: viz
Requires-Dist: matplotlib>=3.5.0; extra == 'viz'
Requires-Dist: plotly>=5.0.0; extra == 'viz'
Requires-Dist: seaborn>=0.12.0; extra == 'viz'
